{
    "fluentMethods": true,
    "relationships": [
        {
            "relationshipName": "user",
            "otherEntityName": "user",
            "relationshipType": "one-to-one",
            "otherEntityField": "login",
            "ownerSide": true,
            "otherEntityRelationshipName": "passwordHistory"
        }
    ],
    "fields": [
        {
            "fieldName": "history_no1",
            "fieldType": "String"
        },
        {
            "fieldName": "history_no2",
            "fieldType": "String"
        },
        {
            "fieldName": "history_no3",
            "fieldType": "String"
        },
        {
            "fieldName": "history_no4",
            "fieldType": "String"
        },
        {
            "fieldName": "history_no5",
            "fieldType": "String"
        }
    ],
    "changelogDate": "20180119031454",
    "dto": "mapstruct",
    "service": "serviceClass",
    "entityTableName": "password_history",
    "pagination": "pagination"
}
